[
    {
        "name": "Olivia",
        "birthYear": "5.02"
    },
    {
        "name": "Olivia",
        "birthdate": "02",
        "fortune": "This is the start of Fortune 02,Fortune 02 has a random fill"
    },
    {
        "name": "Olivia",
        "birthdate": "02",
        "fortune": "This is the start of Fortune 02,Fortune 02 has a random fill"
    },
    {
        "name": "Olivia",
        "birthdate": "",
        "fortune": "Fortune 04 has a random fill,Fortune 04 has three lines,End of Fortune 04"
    },
    {
        "name": "Olivia",
        "birthdate": "02",
        "fortune": "This is the start of Fortune 02,Fortune 02 has a random fill"
    },
    {
        "name": "Olivia",
        "birthdate": "23",
        "fortune": "Fortune 03 has a random fill,Fortune 03 has three lines,End of Fortune 03"
    },
    {
        "name": "Olivia",
        "birthdate": "02",
        "fortune": "This is the start of Fortune 02,Fortune 02 has a random fill"
    },
    {
        "name": "Oliia",
        "birthdate": "75",
        "fortune": "Fortune 04 has a random fill,Fortune 04 has three lines,End of Fortune 04"
    },
    {
        "name": "Olivia",
        "birthdate": "02",
        "fortune": "This is the start of Fortune 02,Fortune 02 has a random fill"
    },
    {
        "name": "Olivia",
        "birthdate": "03",
        "fortune": "This is the start of Fortune 02,Fortune 02 has a random fill"
    },
    {
        "name": "Olivias",
        "birthdate": "29",
        "fortune": "Fortune 03 has a random fill,Fortune 03 has three lines,End of Fortune 03"
    },
    {
        "name": "julia",
        "birthdate": "02",
        "fortune": "This is the start of Fortune 02,Fortune 02 has a random fill"
    },
    {
        "name": "julia",
        "birthdate": "02",
        "fortune": "This is the start of Fortune 02,Fortune 02 has a random fill"
    },
    {
        "name": "olivia",
        "birthdate": "02",
        "fortune": "This is the start of Fortune 02,Fortune 02 has a random fill"
    },
    {
        "name": "olivia",
        "birthdate": "02",
        "fortune": "This is the start of Fortune 02,Fortune 02 has a random fill"
    },
    {
        "name": "Olivia",
        "birthdate": "02",
        "fortune": "This is the start of Fortune 02,Fortune 02 has a random fill"
    },
    {
        "name": "Olivia",
        "birthdate": "02",
        "fortune": "This is the start of Fortune 02,Fortune 02 has a random fill"
    },
    {
        "name": "OLIVIA",
        "birthdate": "02",
        "fortune": "This is the start of Fortune 02,Fortune 02 has a random fill"
    },
    {
        "name": "olivia",
        "birthdate": "02",
        "fortune": "This is the start of Fortune 02,Fortune 02 has a random fill"
    },
    {
        "name": "olivia",
        "birthdate": "02",
        "fortune": "This is the start of Fortune 02,Fortune 02 has a random fill"
    },
    {
        "name": "Olivia",
        "birthdate": "02",
        "fortune": "This is the start of Fortune 02,Fortune 02 has a random fill"
    },
    {
        "name": "Olivia",
        "birthdate": "02",
        "fortune": "This is the start of Fortune 02,Fortune 02 has a random fill"
    },
    {
        "name": "olivia",
        "birthdate": "01",
        "fortune": "This is the start of Fortune 02,Fortune 02 has a random fill"
    },
    {
        "name": "Olivia",
        "birthdate": "02",
        "fortune": "This is the start of Fortune 02,Fortune 02 has a random fill"
    },
    {
        "name": "olivia",
        "birthdate": "02",
        "fortune": "This is the start of Fortune 02,Fortune 02 has a random fill"
    },
    {
        "name": "l",
        "birthdate": "02",
        "fortune": "This is the start of Fortune 02,Fortune 02 has a random fill"
    },
    {
        "name": "olivia",
        "birthdate": "02",
        "fortune": "This is the start of Fortune 02,Fortune 02 has a random fill"
    },
    {
        "name": "Olivia",
        "birthdate": "02",
        "fortune": "This is the start of Fortune 02,Fortune 02 has a random fill"
    },
    {
        "name": "Olivia",
        "birthdate": "02",
        "fortune": "This is the start of Fortune 02,Fortune 02 has a random fill"
    },
    {
        "name": "Olivia",
        "birthdate": "02",
        "fortune": "This is the start of Fortune 02,Fortune 02 has a random fill"
    },
    {
        "name": "olibia",
        "birthdate": "02",
        "fortune": "This is the start of Fortune 02,Fortune 02 has a random fill"
    },
    {
        "name": "olivia",
        "birthdate": "02",
        "fortune": "This is the start of Fortune 02,Fortune 02 has a random fill"
    },
    {
        "name": "olivia",
        "birthdate": "02",
        "fortune": "This is the start of Fortune 02,Fortune 02 has a random fill"
    },
    {
        "name": "olivia",
        "birthdate": "02",
        "fortune": "This is the start of Fortune 02,Fortune 02 has a random fill"
    },
    {
        "name": "ju",
        "birthdate": "20",
        "fortune": "This is the start of Fortune 02,Fortune 02 has a random fill"
    },
    {
        "name": "2",
        "birthdate": "67",
        "fortune": "Fortune 04 has a random fill,Fortune 04 has three lines,End of Fortune 04"
    },
    {
        "name": "juju2",
        "birthdate": "",
        "fortune": "Fortune 04 has a random fill,Fortune 04 has three lines,End of Fortune 04"
    },
    {
        "name": "juju",
        "birthdate": "23",
        "fortune": "Fortune 03 has a random fill,Fortune 03 has three lines,End of Fortune 03"
    },
    {
        "name": "juju",
        "birthdate": "53",
        "fortune": "Fortune 04 has a random fill,Fortune 04 has three lines,End of Fortune 04"
    },
    {
        "name": "olivia",
        "birthdate": "45",
        "fortune": "Fortune 03 has a random fill,Fortune 03 has three lines,End of Fortune 03"
    },
    {
        "name": "olivia",
        "birthdate": "34",
        "fortune": "Fortune 03 has a random fill,Fortune 03 has three lines,End of Fortune 03"
    },
    {
        "name": "olivia",
        "birthdate": "45",
        "fortune": "Fortune 03 has a random fill,Fortune 03 has three lines,End of Fortune 03"
    },
    {
        "name": "olivia",
        "birthdate": "34",
        "fortune": "Fortune 03 has a random fill,Fortune 03 has three lines,End of Fortune 03"
    },
    {
        "name": "oliiva",
        "birthdate": "23",
        "fortune": "Fortune 03 has a random fill,Fortune 03 has three lines,End of Fortune 03"
    },
    {
        "name": "olivia",
        "birthdate": "34",
        "fortune": "Fortune 03 has a random fill,Fortune 03 has three lines,End of Fortune 03"
    },
    {
        "name": "olivia",
        "birthdate": "34",
        "fortune": "Fortune 03 has a random fill,Fortune 03 has three lines,End of Fortune 03"
    },
    {
        "name": "Olivia",
        "birthdate": "32",
        "fortune": "Fortune 03 has a random fill,Fortune 03 has three lines,End of Fortune 03"
    },
    {
        "name": "Olivia",
        "birthdate": "23",
        "fortune": "Fortune 03 has a random fill,Fortune 03 has three lines,End of Fortune 03"
    },
    {
        "name": "Olivis",
        "birthdate": "",
        "fortune": "Fortune 04 has a random fill,Fortune 04 has three lines,End of Fortune 04"
    },
    {
        "name": "olivia",
        "birthdate": "34",
        "fortune": "Fortune 03 has a random fill,Fortune 03 has three lines,End of Fortune 03"
    },
    {
        "name": "olivia",
        "birthdate": "34",
        "fortune": "Fortune 03 has a random fill,Fortune 03 has three lines,End of Fortune 03"
    },
    {
        "name": "olivia",
        "birthdate": "32",
        "fortune": "Fortune 03 has a random fill,Fortune 03 has three lines,End of Fortune 03"
    },
    {
        "name": "olivia",
        "birthdate": "34",
        "fortune": "Fortune 03 has a random fill,Fortune 03 has three lines,End of Fortune 03"
    },
    {
        "name": "olivia",
        "birthdate": "02",
        "fortune": "This is the start of Fortune 02,Fortune 02 has a random fill"
    },
    {
        "name": "oliia",
        "birthdate": "03",
        "fortune": "This is the start of Fortune 02,Fortune 02 has a random fill"
    },
    {
        "name": "olivia",
        "birthdate": "32",
        "fortune": "Fortune 03 has a random fill,Fortune 03 has three lines,End of Fortune 03"
    },
    {
        "name": "olivia",
        "birthdate": "20",
        "fortune": "This is the start of Fortune 02,Fortune 02 has a random fill"
    },
    {
        "name": "olivia",
        "birthdate": "45",
        "fortune": "Fortune 03 has a random fill,Fortune 03 has three lines,End of Fortune 03"
    },
    {
        "name": "Olivia",
        "birthdate": "32",
        "fortune": "Fortune 03 has a random fill,Fortune 03 has three lines,End of Fortune 03"
    },
    {
        "name": "Olivia",
        "birthdate": "32",
        "fortune": "Fortune 03 has a random fill,Fortune 03 has three lines,End of Fortune 03"
    },
    {
        "name": "olivia",
        "birthdate": "32",
        "fortune": "Fortune 03 has a random fill,Fortune 03 has three lines,End of Fortune 03"
    },
    {
        "name": "Olivia",
        "birthdate": "04",
        "fortune": "This is the start of Fortune 02,Fortune 02 has a random fill"
    },
    {
        "name": "julia",
        "birthdate": "43",
        "fortune": "Fortune 03 has a random fill,Fortune 03 has three lines,End of Fortune 03"
    },
    {
        "name": "oliiva",
        "birthdate": "45",
        "fortune": "Fortune 03 has a random fill,Fortune 03 has three lines,End of Fortune 03"
    },
    {
        "name": "olivia",
        "birthdate": "34",
        "fortune": "Fortune 03 has a random fill,Fortune 03 has three lines,End of Fortune 03"
    }
]